ieee_events/__init__.py
ieee_events/client.py
ieee_events/client_basic.py
ieee_events/webapp.py
ieee_events-1.0.1.dist-info/licenses/LICENSE
ieee_events-1.0.1.dist-info/METADATA
ieee_events-1.0.1.dist-info/WHEEL
ieee_events-1.0.1.dist-info/top_level.txt
ieee_events-1.0.1.dist-info/RECORD
