Metadata-Version: 2.4
Name: ieee-events
Version: 1.0.1
Summary: A comprehensive Python client library for the IEEE vTools Events API v7
Home-page: https://github.com/Assem-ElQersh/IEEE-Events-API-Toolkit
Author: IEEE vTools API Contributors
Author-email: IEEE vTools API Contributors <assemsaid35@gmail.com>
License-Expression: MIT
Project-URL: Homepage, https://github.com/Assem-ElQersh/IEEE-Events-API-Toolkit
Project-URL: Documentation, https://events.vtools.ieee.org/api/doc
Project-URL: Repository, https://github.com/Assem-ElQersh/IEEE-Events-API-Toolkit
Project-URL: Bug Tracker, https://github.com/Assem-ElQersh/IEEE-Events-API-Toolkit/issues
Keywords: ieee,events,api,client,vtools,technical-events,conference
Classifier: Development Status :: 5 - Production/Stable
Classifier: Intended Audience :: Developers
Classifier: Intended Audience :: Science/Research
Classifier: Topic :: Software Development :: Libraries :: Python Modules
Classifier: Topic :: Scientific/Engineering
Classifier: Programming Language :: Python :: 3
Classifier: Programming Language :: Python :: 3.8
Classifier: Programming Language :: Python :: 3.9
Classifier: Programming Language :: Python :: 3.10
Classifier: Programming Language :: Python :: 3.11
Classifier: Programming Language :: Python :: 3.12
Classifier: Operating System :: OS Independent
Requires-Python: >=3.8
License-File: LICENSE
Requires-Dist: requests>=2.31.0
Provides-Extra: webapp
Requires-Dist: Flask>=3.0.0; extra == "webapp"
Provides-Extra: dev
Requires-Dist: pytest>=7.0.0; extra == "dev"
Requires-Dist: pytest-cov>=4.0.0; extra == "dev"
Requires-Dist: black>=23.0.0; extra == "dev"
Requires-Dist: flake8>=6.0.0; extra == "dev"
Requires-Dist: mypy>=1.0.0; extra == "dev"
Dynamic: license-file
